vgif/main.py
vgif/video2gif.py
vgif-1.0.6.dist-info/LICENSE
vgif-1.0.6.dist-info/METADATA
vgif-1.0.6.dist-info/WHEEL
vgif-1.0.6.dist-info/entry_points.txt
vgif-1.0.6.dist-info/top_level.txt
vgif-1.0.6.dist-info/RECORD
